yolo6/__init__.py
yolo6-0.0.1.dist-info/METADATA
yolo6-0.0.1.dist-info/WHEEL
yolo6-0.0.1.dist-info/top_level.txt
yolo6-0.0.1.dist-info/RECORD
